youtube2ipfs/__init__.py
youtube2ipfs/youtube2ipfs.py
youtube2ipfs-0.3.dist-info/LICENSE
youtube2ipfs-0.3.dist-info/METADATA
youtube2ipfs-0.3.dist-info/WHEEL
youtube2ipfs-0.3.dist-info/entry_points.txt
youtube2ipfs-0.3.dist-info/top_level.txt
youtube2ipfs-0.3.dist-info/RECORD
