Metadata-Version: 2.1
Name: youtube2ipfs
Version: 0.3
Summary: Download videos from YouTube (and similar video platforms) and add them to IPFS.
Home-page: https://github.com/dokterbob/youtube2ipfs
Author: Mathijs de Bruin
Author-email: mathijs@mathijsfietst.nl
License: UNKNOWN
Platform: UNKNOWN
Classifier: Development Status :: 5 - Production/Stable
Classifier: Environment :: Console
Classifier: Intended Audience :: End Users/Desktop
Classifier: Intended Audience :: Developers
Classifier: Intended Audience :: System Administrators
Classifier: License :: OSI Approved :: GNU Affero General Public License v3
Classifier: Operating System :: OS Independent
Classifier: Programming Language :: Python
Classifier: Programming Language :: Python :: 3.8
Classifier: Topic :: Utilities
Requires-Dist: ipfshttpclient (>=2.25.1)
Requires-Dist: youtube-dl (>=2021.12.17)
